MANIFEST.in
README.rst
setup.py
pygmy/__init__.py
pygmy/test_settings.py
pygmy.egg-info/PKG-INFO
pygmy.egg-info/SOURCES.txt
pygmy.egg-info/dependency_links.txt
pygmy.egg-info/not-zip-safe
pygmy.egg-info/requires.txt
pygmy.egg-info/top_level.txt
pygmy/templatetags/__init__.py
pygmy/templatetags/pygmy.py
pygmy/tests/__init__.py
pygmy/tests/models.py
pygmy/tests/testrunner.py
pygmy/tests/tests.py