Metadata-Version: 1.0
Name: pygmy
Version: 0.2.0
Summary: UNKNOWN
Home-page: https://github.com/mattack108/pygmy
Author: Matt Lenc
Author-email: matt.lenc@gmail.com
License: UNKNOWN
Platform: UNKNOWN
